[
  {
    "domain": ".x.com",
    "expiry": 1742199613,
    "httpOnly": false,
    "name": "gt",
    "path": "/",
    "sameSite": "Lax",
    "secure": true,
    "value": "1901511367523512521"
  },
  {
    "domain": ".x.com",
    "expiry": 1776750613,
    "httpOnly": false,
    "name": "guest_id_marketing",
    "path": "/",
    "sameSite": "None",
    "secure": true,
    "value": "v1%3A174219061302085631"
  },
  {
    "domain": ".x.com",
    "expiry": 1776750613,
    "httpOnly": false,
    "name": "personalization_id",
    "path": "/",
    "sameSite": "None",
    "secure": true,
    "value": "\"v1_loBKZQzJaVdO1z2Jo685+g==\""
  },
  {
    "domain": ".x.com",
    "expiry": 1742277014,
    "httpOnly": true,
    "name": "att",
    "path": "/",
    "sameSite": "None",
    "secure": true,
    "value": "1-mJWtGqYZGJOAkziJSBgW282t0yMY1LQhVSP5YdJi"
  },
  {
    "domain": ".x.com",
    "expiry": 1742192412,
    "httpOnly": true,
    "name": "__cf_bm",
    "path": "/",
    "sameSite": "None",
    "secure": true,
    "value": "rmOqNrL8rUUBArnX0QH8_FLOgHQKXN0xYZolFHJktjg-1742190613-1.0.1.1-k0PD9XjnUTLPnCxnTUAonPhgAHYLMjntA8Ohn2q2Ma2mHBQxLJ3WPl0xCqgn1TJh5VO5w1WT8zcjXsAzZE4DkHSKKaILhbsxc4CX6xzypT4"
  },
  {
    "domain": ".x.com",
    "expiry": 1776750612,
    "httpOnly": false,
    "name": "guest_id",
    "path": "/",
    "sameSite": "None",
    "secure": true,
    "value": "v1%3A174219061302085631"
  },
  {
    "domain": ".x.com",
    "expiry": 1776750613,
    "httpOnly": false,
    "name": "guest_id_ads",
    "path": "/",
    "sameSite": "None",
    "secure": true,
    "value": "v1%3A174219061302085631"
  }
]